MdnHttpZhongwenWendang20171202/README.md
MdnHttpZhongwenWendang20171202/__init__.py
MdnHttpZhongwenWendang20171202/__main__.py
MdnHttpZhongwenWendang20171202/file.epub
MdnHttpZhongwenWendang20171202/index.html
MdnHttpZhongwenWendang20171202/css/__init__.py
MdnHttpZhongwenWendang20171202/css/annotations.css
MdnHttpZhongwenWendang20171202/css/main.css
MdnHttpZhongwenWendang20171202/css/normalize.css
MdnHttpZhongwenWendang20171202/css/popup.css
MdnHttpZhongwenWendang20171202/font/__init__.py
MdnHttpZhongwenWendang20171202/font/fontello.eot
MdnHttpZhongwenWendang20171202/font/fontello.svg
MdnHttpZhongwenWendang20171202/font/fontello.ttf
MdnHttpZhongwenWendang20171202/font/fontello.woff
MdnHttpZhongwenWendang20171202/img/__init__.py
MdnHttpZhongwenWendang20171202/img/annotator-glyph-sprite.png
MdnHttpZhongwenWendang20171202/img/annotator-icon-sprite.png
MdnHttpZhongwenWendang20171202/img/apple-touch-icon.png
MdnHttpZhongwenWendang20171202/img/cancelfullscreen.png
MdnHttpZhongwenWendang20171202/img/close.png
MdnHttpZhongwenWendang20171202/img/fullscreen.png
MdnHttpZhongwenWendang20171202/img/loader.gif
MdnHttpZhongwenWendang20171202/img/menu-icon.png
MdnHttpZhongwenWendang20171202/img/save.png
MdnHttpZhongwenWendang20171202/img/saved.png
MdnHttpZhongwenWendang20171202/img/settings-s.png
MdnHttpZhongwenWendang20171202/img/settings.png
MdnHttpZhongwenWendang20171202/img/star.png
MdnHttpZhongwenWendang20171202/js/__init__.py
MdnHttpZhongwenWendang20171202/js/epub.js
MdnHttpZhongwenWendang20171202/js/epub.min.js
MdnHttpZhongwenWendang20171202/js/epub.min.map
MdnHttpZhongwenWendang20171202/js/hooks.min.js
MdnHttpZhongwenWendang20171202/js/hooks.min.map
MdnHttpZhongwenWendang20171202/js/reader.js
MdnHttpZhongwenWendang20171202/js/reader.js.map
MdnHttpZhongwenWendang20171202/js/reader.min.js
MdnHttpZhongwenWendang20171202/js/reader.min.map
MdnHttpZhongwenWendang20171202/js/hooks/__init__.py
MdnHttpZhongwenWendang20171202/js/hooks/extensions/__init__.py
mdn_http_zhongwen_wendang_20171202-2024.3.2.0.dist-info/METADATA
mdn_http_zhongwen_wendang_20171202-2024.3.2.0.dist-info/WHEEL
mdn_http_zhongwen_wendang_20171202-2024.3.2.0.dist-info/entry_points.txt
mdn_http_zhongwen_wendang_20171202-2024.3.2.0.dist-info/top_level.txt
mdn_http_zhongwen_wendang_20171202-2024.3.2.0.dist-info/RECORD
